{"ranking":[{"name":"Argentina","value":178626},{"name":"Australia","value":369786},{"name":"Belgium","value":311304},{"name":"Canada","value":388610},{"name":"China","value":333320},{"name":"France","value":537598},{"name":"Germany","value":609298},{"name":"India","value":273253},{"name":"Indonesia","value":348071},{"name":"Japan","value":498313},{"name":"Mexico","value":152307},{"name":"Poland","value":342886},{"name":"Russia","value":245584},{"name":"Singapore","value":211199},{"name":"South Korea","value":319346},{"name":"Ukraine","value":212173},{"name":"United Kingdom","value":402610},{"name":"United States of America","value":388174},{"name":"Vietnam","value":204930}]}
