{"ranking":[{"name":"Argentina","value":179680},{"name":"Australia","value":380329},{"name":"Belgium","value":312342},{"name":"Canada","value":384823},{"name":"China","value":331448},{"name":"France","value":533273},{"name":"Germany","value":607021},{"name":"India","value":267393},{"name":"Indonesia","value":348959},{"name":"Japan","value":492333},{"name":"Mexico","value":161555},{"name":"Poland","value":341995},{"name":"Russia","value":243601},{"name":"Singapore","value":209103},{"name":"South Korea","value":311061},{"name":"Ukraine","value":208006},{"name":"United Kingdom","value":399210},{"name":"United States of America","value":383063},{"name":"Vietnam","value":212822}]}
