{"ranking":[{"name":"Argentina","value":186727},{"name":"Australia","value":371402},{"name":"Belgium","value":314621},{"name":"Canada","value":400236},{"name":"China","value":335504},{"name":"France","value":544942},{"name":"Germany","value":616821},{"name":"India","value":282986},{"name":"Indonesia","value":349521},{"name":"Japan","value":501556},{"name":"Mexico","value":151110},{"name":"Poland","value":350117},{"name":"Russia","value":242054},{"name":"Singapore","value":218296},{"name":"South Korea","value":317229},{"name":"Ukraine","value":227761},{"name":"United Kingdom","value":397064},{"name":"United States of America","value":400586},{"name":"Vietnam","value":202257}]}
