{"ranking":[{"name":"Argentina","value":180313},{"name":"Australia","value":379797},{"name":"Belgium","value":311325},{"name":"Canada","value":382433},{"name":"China","value":325444},{"name":"France","value":534036},{"name":"Germany","value":614281},{"name":"India","value":250603},{"name":"Indonesia","value":360409},{"name":"Japan","value":504272},{"name":"Mexico","value":167268},{"name":"Poland","value":339982},{"name":"Russia","value":247537},{"name":"Singapore","value":205046},{"name":"South Korea","value":306764},{"name":"Ukraine","value":198784},{"name":"United Kingdom","value":391526},{"name":"United States of America","value":365388},{"name":"Vietnam","value":221042}]}
