{"ranking":[{"name":"Argentina","value":179951},{"name":"Australia","value":377453},{"name":"Belgium","value":318933},{"name":"Canada","value":385208},{"name":"China","value":327040},{"name":"France","value":533135},{"name":"Germany","value":620478},{"name":"India","value":243165},{"name":"Indonesia","value":364276},{"name":"Japan","value":502506},{"name":"Mexico","value":170160},{"name":"Poland","value":341346},{"name":"Russia","value":248082},{"name":"Singapore","value":203397},{"name":"South Korea","value":303130},{"name":"Ukraine","value":198389},{"name":"United Kingdom","value":395935},{"name":"United States of America","value":366072},{"name":"Vietnam","value":215338}]}
