{"ranking":[{"name":"Argentina","value":180883},{"name":"Australia","value":371899},{"name":"Belgium","value":315895},{"name":"Canada","value":405207},{"name":"China","value":340866},{"name":"France","value":540661},{"name":"Germany","value":620535},{"name":"India","value":285079},{"name":"Indonesia","value":347445},{"name":"Japan","value":510024},{"name":"Mexico","value":148332},{"name":"Poland","value":354699},{"name":"Russia","value":237681},{"name":"Singapore","value":218889},{"name":"South Korea","value":311679},{"name":"Ukraine","value":235354},{"name":"United Kingdom","value":399473},{"name":"United States of America","value":405693},{"name":"Vietnam","value":206849}]}
