{"ranking":[{"name":"Argentina","value":179344},{"name":"Australia","value":384317},{"name":"Belgium","value":318889},{"name":"Canada","value":386530},{"name":"China","value":314458},{"name":"France","value":529595},{"name":"Germany","value":612069},{"name":"India","value":244863},{"name":"Indonesia","value":351417},{"name":"Japan","value":496531},{"name":"Mexico","value":162970},{"name":"Poland","value":335100},{"name":"Russia","value":232130},{"name":"Singapore","value":197607},{"name":"South Korea","value":288117},{"name":"Ukraine","value":195503},{"name":"United Kingdom","value":401178},{"name":"United States of America","value":369307},{"name":"Vietnam","value":204805}]}
