{"ranking":[{"name":"Argentina","value":184475},{"name":"Australia","value":383175},{"name":"Belgium","value":325571},{"name":"Canada","value":400676},{"name":"China","value":329133},{"name":"France","value":532092},{"name":"Germany","value":615975},{"name":"India","value":246177},{"name":"Indonesia","value":349553},{"name":"Japan","value":504600},{"name":"Mexico","value":164322},{"name":"Poland","value":337669},{"name":"Russia","value":220886},{"name":"Singapore","value":198556},{"name":"South Korea","value":288124},{"name":"Ukraine","value":195530},{"name":"United Kingdom","value":404837},{"name":"United States of America","value":371392},{"name":"Vietnam","value":208700}]}
