{"ranking":[{"name":"Argentina","value":181299},{"name":"Australia","value":373426},{"name":"Belgium","value":317676},{"name":"Canada","value":401089},{"name":"China","value":346856},{"name":"France","value":542075},{"name":"Germany","value":623096},{"name":"India","value":288363},{"name":"Indonesia","value":349098},{"name":"Japan","value":509926},{"name":"Mexico","value":147546},{"name":"Poland","value":356630},{"name":"Russia","value":240114},{"name":"Singapore","value":223068},{"name":"South Korea","value":310114},{"name":"Ukraine","value":239918},{"name":"United Kingdom","value":405019},{"name":"United States of America","value":408982},{"name":"Vietnam","value":203465}]}
