{"ranking":[{"name":"Argentina","value":180450},{"name":"Australia","value":370597},{"name":"Belgium","value":315021},{"name":"Canada","value":404331},{"name":"China","value":340322},{"name":"France","value":538569},{"name":"Germany","value":619613},{"name":"India","value":283682},{"name":"Indonesia","value":346485},{"name":"Japan","value":506962},{"name":"Mexico","value":146369},{"name":"Poland","value":353107},{"name":"Russia","value":237113},{"name":"Singapore","value":218727},{"name":"South Korea","value":311195},{"name":"Ukraine","value":236349},{"name":"United Kingdom","value":398263},{"name":"United States of America","value":402987},{"name":"Vietnam","value":206553}]}
