{"ranking":[{"name":"Argentina","value":179090},{"name":"Australia","value":366021},{"name":"Belgium","value":312170},{"name":"Canada","value":390101},{"name":"China","value":339107},{"name":"France","value":534607},{"name":"Germany","value":613653},{"name":"India","value":282051},{"name":"Indonesia","value":342179},{"name":"Japan","value":501820},{"name":"Mexico","value":144392},{"name":"Poland","value":349570},{"name":"Russia","value":235627},{"name":"Singapore","value":217225},{"name":"South Korea","value":307917},{"name":"Ukraine","value":233356},{"name":"United Kingdom","value":394461},{"name":"United States of America","value":398738},{"name":"Vietnam","value":205189}]}
