{"ranking":[{"name":"Argentina","value":179677},{"name":"Australia","value":371564},{"name":"Belgium","value":312102},{"name":"Canada","value":391184},{"name":"China","value":334742},{"name":"France","value":542145},{"name":"Germany","value":612434},{"name":"India","value":273982},{"name":"Indonesia","value":346428},{"name":"Japan","value":502492},{"name":"Mexico","value":152428},{"name":"Poland","value":345281},{"name":"Russia","value":246940},{"name":"Singapore","value":215694},{"name":"South Korea","value":324929},{"name":"Ukraine","value":214148},{"name":"United Kingdom","value":408719},{"name":"United States of America","value":391861},{"name":"Vietnam","value":210492}]}
