{"ranking":[{"name":"Argentina","value":181460},{"name":"Australia","value":380741},{"name":"Belgium","value":320661},{"name":"Canada","value":387795},{"name":"China","value":328280},{"name":"France","value":540655},{"name":"Germany","value":625201},{"name":"India","value":245357},{"name":"Indonesia","value":364694},{"name":"Japan","value":508260},{"name":"Mexico","value":171177},{"name":"Poland","value":345267},{"name":"Russia","value":248401},{"name":"Singapore","value":204652},{"name":"South Korea","value":305360},{"name":"Ukraine","value":199147},{"name":"United Kingdom","value":399190},{"name":"United States of America","value":367413},{"name":"Vietnam","value":220122}]}
