{"ranking":[{"name":"Argentina","value":184445},{"name":"Australia","value":390260},{"name":"Belgium","value":325902},{"name":"Canada","value":411008},{"name":"China","value":332235},{"name":"France","value":531493},{"name":"Germany","value":619818},{"name":"India","value":241156},{"name":"Indonesia","value":345236},{"name":"Japan","value":503528},{"name":"Mexico","value":166233},{"name":"Poland","value":333994},{"name":"Russia","value":223219},{"name":"Singapore","value":199494},{"name":"South Korea","value":293522},{"name":"Ukraine","value":194867},{"name":"United Kingdom","value":422927},{"name":"United States of America","value":377057},{"name":"Vietnam","value":214857}]}
