{"ranking":[{"name":"Argentina","value":181884},{"name":"Australia","value":388617},{"name":"Belgium","value":321724},{"name":"Canada","value":409889},{"name":"China","value":330014},{"name":"France","value":530842},{"name":"Germany","value":613002},{"name":"India","value":246496},{"name":"Indonesia","value":351259},{"name":"Japan","value":500238},{"name":"Mexico","value":164332},{"name":"Poland","value":334473},{"name":"Russia","value":220383},{"name":"Singapore","value":199287},{"name":"South Korea","value":288170},{"name":"Ukraine","value":195716},{"name":"United Kingdom","value":413219},{"name":"United States of America","value":375813},{"name":"Vietnam","value":209655}]}
