{"ranking":[{"name":"Argentina","value":180858},{"name":"Australia","value":392383},{"name":"Belgium","value":320608},{"name":"Canada","value":408346},{"name":"China","value":329512},{"name":"France","value":526310},{"name":"Germany","value":611527},{"name":"India","value":240355},{"name":"Indonesia","value":340338},{"name":"Japan","value":498601},{"name":"Mexico","value":163301},{"name":"Poland","value":329197},{"name":"Russia","value":219728},{"name":"Singapore","value":198568},{"name":"South Korea","value":289073},{"name":"Ukraine","value":194986},{"name":"United Kingdom","value":412347},{"name":"United States of America","value":375228},{"name":"Vietnam","value":209432}]}
