{"ranking":[{"name":"Argentina","value":180084},{"name":"Australia","value":369872},{"name":"Belgium","value":314596},{"name":"Canada","value":394971},{"name":"China","value":343405},{"name":"France","value":539295},{"name":"Germany","value":620220},{"name":"India","value":285015},{"name":"Indonesia","value":348346},{"name":"Japan","value":505461},{"name":"Mexico","value":146644},{"name":"Poland","value":354038},{"name":"Russia","value":238690},{"name":"Singapore","value":220061},{"name":"South Korea","value":309734},{"name":"Ukraine","value":237318},{"name":"United Kingdom","value":399813},{"name":"United States of America","value":402626},{"name":"Vietnam","value":202782}]}
