{"ranking":[{"name":"Argentina","value":180035},{"name":"Australia","value":379931},{"name":"Belgium","value":316812},{"name":"Canada","value":385909},{"name":"China","value":327030},{"name":"France","value":537705},{"name":"Germany","value":622143},{"name":"India","value":245391},{"name":"Indonesia","value":361976},{"name":"Japan","value":506490},{"name":"Mexico","value":170041},{"name":"Poland","value":344071},{"name":"Russia","value":248073},{"name":"Singapore","value":204015},{"name":"South Korea","value":304343},{"name":"Ukraine","value":198555},{"name":"United Kingdom","value":397123},{"name":"United States of America","value":366242},{"name":"Vietnam","value":222548}]}
