{"ranking":[{"name":"Argentina","value":178271},{"name":"Australia","value":365574},{"name":"Belgium","value":311801},{"name":"Canada","value":390441},{"name":"China","value":341083},{"name":"France","value":531501},{"name":"Germany","value":612732},{"name":"India","value":282601},{"name":"Indonesia","value":344088},{"name":"Japan","value":500776},{"name":"Mexico","value":144845},{"name":"Poland","value":357143},{"name":"Russia","value":243799},{"name":"Singapore","value":223433},{"name":"South Korea","value":312461},{"name":"Ukraine","value":240767},{"name":"United Kingdom","value":398228},{"name":"United States of America","value":402066},{"name":"Vietnam","value":201644}]}
