{"ranking":[{"name":"Argentina","value":180880},{"name":"Australia","value":370096},{"name":"Belgium","value":312309},{"name":"Canada","value":391522},{"name":"China","value":331352},{"name":"France","value":541783},{"name":"Germany","value":613027},{"name":"India","value":280249},{"name":"Indonesia","value":349119},{"name":"Japan","value":502042},{"name":"Mexico","value":153068},{"name":"Poland","value":344004},{"name":"Russia","value":248497},{"name":"Singapore","value":213606},{"name":"South Korea","value":322594},{"name":"Ukraine","value":215233},{"name":"United Kingdom","value":403929},{"name":"United States of America","value":392612},{"name":"Vietnam","value":206597}]}
