{"ranking":[{"name":"Argentina","value":184300},{"name":"Australia","value":368715},{"name":"Belgium","value":314440},{"name":"Canada","value":393514},{"name":"China","value":332400},{"name":"France","value":542069},{"name":"Germany","value":606469},{"name":"India","value":279070},{"name":"Indonesia","value":349384},{"name":"Japan","value":497395},{"name":"Mexico","value":152009},{"name":"Poland","value":348160},{"name":"Russia","value":248379},{"name":"Singapore","value":218626},{"name":"South Korea","value":314945},{"name":"Ukraine","value":226323},{"name":"United Kingdom","value":392957},{"name":"United States of America","value":397819},{"name":"Vietnam","value":203562}]}
