{"ranking":[{"name":"Argentina","value":186360},{"name":"Australia","value":370835},{"name":"Belgium","value":316802},{"name":"Canada","value":395799},{"name":"China","value":333928},{"name":"France","value":543756},{"name":"Germany","value":610398},{"name":"India","value":279918},{"name":"Indonesia","value":350646},{"name":"Japan","value":501039},{"name":"Mexico","value":153477},{"name":"Poland","value":346569},{"name":"Russia","value":246074},{"name":"Singapore","value":218284},{"name":"South Korea","value":319711},{"name":"Ukraine","value":220187},{"name":"United Kingdom","value":408242},{"name":"United States of America","value":399996},{"name":"Vietnam","value":204943}]}
