{"ranking":[{"name":"Argentina","value":179241},{"name":"Australia","value":368880},{"name":"Belgium","value":309370},{"name":"Canada","value":387554},{"name":"China","value":332478},{"name":"France","value":535281},{"name":"Germany","value":607698},{"name":"India","value":275432},{"name":"Indonesia","value":347292},{"name":"Japan","value":497361},{"name":"Mexico","value":152083},{"name":"Poland","value":341843},{"name":"Russia","value":245179},{"name":"Singapore","value":210741},{"name":"South Korea","value":318820},{"name":"Ukraine","value":211716},{"name":"United Kingdom","value":399904},{"name":"United States of America","value":387297},{"name":"Vietnam","value":204500}]}
